[{"line":4,"uri":"file:src/test/resources/features/F1_RSSPCalculator.feature","id":"as-a-user-i-want-to-calculate-how-much-money-i-can-save-in-a-registered-retirement-savings","keyword":"Feature","name":"As a user I want to calculate how much money I can save in a registered retirement savings","description":"  plan so that reach my retirement goals","elements":[{"line":7,"type":"background","keyword":"Background","name":"","description":"","steps":[{"keyword":"Given ","line":8,"match":{"location":"stepdefinitions.F1_RRSPCalculator.user_launches_the_application()"},"name":"User launches the application","result":{"duration":1185575300,"status":"passed"}},{"keyword":"And ","line":9,"match":{"location":"stepdefinitions.F1_RRSPCalculator.user_should_be_at_the_homepage()"},"name":"User should be at the homepage","result":{"duration":1051317100,"status":"passed"}},{"keyword":"And ","line":10,"match":{"location":"stepdefinitions.F1_RRSPCalculator.userAcceptsThePrivacySettings()"},"name":"User accepts the privacy settings","result":{"duration":154417900,"status":"passed"}},{"keyword":"And ","line":11,"match":{"location":"stepdefinitions.F1_RRSPCalculator.user_sees_the_investments_tab()"},"name":"User sees the Investments tab","result":{"duration":28973600,"status":"passed"}},{"keyword":"And ","line":12,"match":{"location":"stepdefinitions.F1_RRSPCalculator.user_hovers_over_investments_tab()"},"name":"User hovers over Investments tab","result":{"duration":144089800,"status":"passed"}},{"keyword":"And ","line":13,"match":{"location":"stepdefinitions.F1_RRSPCalculator.user_clicks_rrsp_calculator_link()"},"name":"User clicks RRSP Calculator link","result":{"duration":1200977300,"status":"passed"}},{"keyword":"And ","line":14,"match":{"location":"stepdefinitions.F1_RRSPCalculator.user_should_be_at_the_rrsp_calculator_page()"},"name":"User should be at the rrsp calculator page","result":{"duration":29388600,"status":"passed"}},{"keyword":"And ","line":15,"match":{"location":"stepdefinitions.F1_RRSPCalculator.user_should_see_the_calculator_fields()"},"name":"User should see the Calculator fields","result":{"duration":1074740300,"status":"passed"}}]},{"start_timestamp":"2025-10-24T18:57:07.317Z","line":18,"id":"as-a-user-i-want-to-calculate-how-much-money-i-can-save-in-a-registered-retirement-savings;user-should-be-able-to-click-on-rate-of-return-tooltip-to-get-a-message-explaining-what-to-input","type":"scenario","keyword":"Scenario","name":"User should be able to click on rate of return tooltip to get a message explaining what to input","description":"","steps":[{"keyword":"Given ","line":19,"match":{"location":"stepdefinitions.F1_RRSPCalculator.userCanSeeTheTooltipNextToTheRateField()"},"name":"User can see the tooltip next to the rate field","result":{"duration":20688900,"status":"passed"}},{"keyword":"When ","line":20,"match":{"location":"stepdefinitions.F1_RRSPCalculator.userClicksTheTooltipForRateField()"},"name":"User clicks the tooltip for rate field","result":{"duration":78975400,"status":"passed"}},{"keyword":"And ","line":21,"match":{"location":"stepdefinitions.F1_RRSPCalculator.userCanSeeTooltipContent()"},"name":"User can see tooltip content","result":{"duration":58633600,"status":"passed"}},{"keyword":"Then ","line":22,"match":{"location":"stepdefinitions.F1_RRSPCalculator.userShouldSeeAMessage(java.lang.String)","arguments":[{"val":"\"This is how much growth you expect to see in your account between now and retirement.\"","offset":26}]},"name":"User should see a message \"This is how much growth you expect to see in your account between now and retirement.\"","result":{"duration":22342900,"status":"passed"}}],"before":[{"match":{"location":"stepdefinitions.Hooks.init()"},"result":{"duration":1210193500,"status":"passed"}}],"after":[{"match":{"location":"stepdefinitions.Hooks.tearDown()"},"result":{"duration":222007000,"status":"passed"}}],"tags":[{"name":"@RRSP"},{"name":"@RegressionTest"},{"name":"@RateFieldTooltip"}]},{"line":7,"type":"background","keyword":"Background","name":"","description":"","steps":[{"keyword":"Given ","line":8,"match":{"location":"stepdefinitions.F1_RRSPCalculator.user_launches_the_application()"},"name":"User launches the application","result":{"duration":1213888300,"status":"passed"}},{"keyword":"And ","line":9,"match":{"location":"stepdefinitions.F1_RRSPCalculator.user_should_be_at_the_homepage()"},"name":"User should be at the homepage","result":{"duration":1044185300,"status":"passed"}},{"keyword":"And ","line":10,"match":{"location":"stepdefinitions.F1_RRSPCalculator.userAcceptsThePrivacySettings()"},"name":"User accepts the privacy settings","result":{"duration":151683100,"status":"passed"}},{"keyword":"And ","line":11,"match":{"location":"stepdefinitions.F1_RRSPCalculator.user_sees_the_investments_tab()"},"name":"User sees the Investments tab","result":{"duration":24927300,"status":"passed"}},{"keyword":"And ","line":12,"match":{"location":"stepdefinitions.F1_RRSPCalculator.user_hovers_over_investments_tab()"},"name":"User hovers over Investments tab","result":{"duration":165091900,"status":"passed"}},{"keyword":"And ","line":13,"match":{"location":"stepdefinitions.F1_RRSPCalculator.user_clicks_rrsp_calculator_link()"},"name":"User clicks RRSP Calculator link","result":{"duration":1162669200,"status":"passed"}},{"keyword":"And ","line":14,"match":{"location":"stepdefinitions.F1_RRSPCalculator.user_should_be_at_the_rrsp_calculator_page()"},"name":"User should be at the rrsp calculator page","result":{"duration":27010300,"status":"passed"}},{"keyword":"And ","line":15,"match":{"location":"stepdefinitions.F1_RRSPCalculator.user_should_see_the_calculator_fields()"},"name":"User should see the Calculator fields","result":{"duration":1072282000,"status":"passed"}}]},{"start_timestamp":"2025-10-24T18:57:13.833Z","line":30,"id":"as-a-user-i-want-to-calculate-how-much-money-i-can-save-in-a-registered-retirement-savings;user-should-get-an-error-when-entering-rate-of-return-lower-than-1%-or-higher-than-1000%;;2","type":"scenario","keyword":"Scenario Outline","name":"User should get an error when entering rate of return lower than 1% or higher than 1000%","description":"","steps":[{"keyword":"When ","line":26,"match":{"location":"stepdefinitions.F1_RRSPCalculator.userInputsAnInvalidRateOfReturn(java.lang.String)","arguments":[{"val":"\"-1\"","offset":38}]},"name":"User inputs an invalid rate of return \"-1\"","result":{"duration":119608100,"status":"passed"}},{"keyword":"Then ","line":27,"match":{"location":"stepdefinitions.F1_RRSPCalculator.userShouldBeAbleToSeeTheMessage(java.lang.String)","arguments":[{"val":"\"Please select a rate between 1% and 1000%\"","offset":39}]},"name":"User should be able to see the message \"Please select a rate between 1% and 1000%\"","result":{"duration":37898800,"status":"passed"}}],"before":[{"match":{"location":"stepdefinitions.Hooks.init()"},"result":{"duration":844581600,"status":"passed"}}],"after":[{"match":{"location":"stepdefinitions.Hooks.tearDown()"},"result":{"duration":215155700,"status":"passed"}}],"tags":[{"name":"@RRSP"},{"name":"@RegressionTest"},{"name":"@IncorrectReturnRate"}]},{"line":7,"type":"background","keyword":"Background","name":"","description":"","steps":[{"keyword":"Given ","line":8,"match":{"location":"stepdefinitions.F1_RRSPCalculator.user_launches_the_application()"},"name":"User launches the application","result":{"duration":1175201200,"status":"passed"}},{"keyword":"And ","line":9,"match":{"location":"stepdefinitions.F1_RRSPCalculator.user_should_be_at_the_homepage()"},"name":"User should be at the homepage","result":{"duration":1038507600,"status":"passed"}},{"keyword":"And ","line":10,"match":{"location":"stepdefinitions.F1_RRSPCalculator.userAcceptsThePrivacySettings()"},"name":"User accepts the privacy settings","result":{"duration":168683700,"status":"passed"}},{"keyword":"And ","line":11,"match":{"location":"stepdefinitions.F1_RRSPCalculator.user_sees_the_investments_tab()"},"name":"User sees the Investments tab","result":{"duration":26841200,"status":"passed"}},{"keyword":"And ","line":12,"match":{"location":"stepdefinitions.F1_RRSPCalculator.user_hovers_over_investments_tab()"},"name":"User hovers over Investments tab","result":{"duration":138440200,"status":"passed"}},{"keyword":"And ","line":13,"match":{"location":"stepdefinitions.F1_RRSPCalculator.user_clicks_rrsp_calculator_link()"},"name":"User clicks RRSP Calculator link","result":{"duration":1236562300,"status":"passed"}},{"keyword":"And ","line":14,"match":{"location":"stepdefinitions.F1_RRSPCalculator.user_should_be_at_the_rrsp_calculator_page()"},"name":"User should be at the rrsp calculator page","result":{"duration":25453900,"status":"passed"}},{"keyword":"And ","line":15,"match":{"location":"stepdefinitions.F1_RRSPCalculator.user_should_see_the_calculator_fields()"},"name":"User should see the Calculator fields","result":{"duration":1060635200,"status":"passed"}}]},{"start_timestamp":"2025-10-24T18:57:19.921Z","line":31,"id":"as-a-user-i-want-to-calculate-how-much-money-i-can-save-in-a-registered-retirement-savings;user-should-get-an-error-when-entering-rate-of-return-lower-than-1%-or-higher-than-1000%;;3","type":"scenario","keyword":"Scenario Outline","name":"User should get an error when entering rate of return lower than 1% or higher than 1000%","description":"","steps":[{"keyword":"When ","line":26,"match":{"location":"stepdefinitions.F1_RRSPCalculator.userInputsAnInvalidRateOfReturn(java.lang.String)","arguments":[{"val":"\"0\"","offset":38}]},"name":"User inputs an invalid rate of return \"0\"","result":{"duration":117841700,"status":"passed"}},{"keyword":"Then ","line":27,"match":{"location":"stepdefinitions.F1_RRSPCalculator.userShouldBeAbleToSeeTheMessage(java.lang.String)","arguments":[{"val":"\"Please select a rate between 1% and 1000%\"","offset":39}]},"name":"User should be able to see the message \"Please select a rate between 1% and 1000%\"","result":{"duration":37996800,"status":"passed"}}],"before":[{"match":{"location":"stepdefinitions.Hooks.init()"},"result":{"duration":878558000,"status":"passed"}}],"after":[{"match":{"location":"stepdefinitions.Hooks.tearDown()"},"result":{"duration":200015600,"status":"passed"}}],"tags":[{"name":"@RRSP"},{"name":"@RegressionTest"},{"name":"@IncorrectReturnRate"}]},{"line":7,"type":"background","keyword":"Background","name":"","description":"","steps":[{"keyword":"Given ","line":8,"match":{"location":"stepdefinitions.F1_RRSPCalculator.user_launches_the_application()"},"name":"User launches the application","result":{"duration":1165281900,"status":"passed"}},{"keyword":"And ","line":9,"match":{"location":"stepdefinitions.F1_RRSPCalculator.user_should_be_at_the_homepage()"},"name":"User should be at the homepage","result":{"duration":1030606800,"status":"passed"}},{"keyword":"And ","line":10,"match":{"location":"stepdefinitions.F1_RRSPCalculator.userAcceptsThePrivacySettings()"},"name":"User accepts the privacy settings","result":{"duration":141127800,"status":"passed"}},{"keyword":"And ","line":11,"match":{"location":"stepdefinitions.F1_RRSPCalculator.user_sees_the_investments_tab()"},"name":"User sees the Investments tab","result":{"duration":25422100,"status":"passed"}},{"keyword":"And ","line":12,"match":{"location":"stepdefinitions.F1_RRSPCalculator.user_hovers_over_investments_tab()"},"name":"User hovers over Investments tab","result":{"duration":150414100,"status":"passed"}},{"keyword":"And ","line":13,"match":{"location":"stepdefinitions.F1_RRSPCalculator.user_clicks_rrsp_calculator_link()"},"name":"User clicks RRSP Calculator link","result":{"duration":1205771000,"status":"passed"}},{"keyword":"And ","line":14,"match":{"location":"stepdefinitions.F1_RRSPCalculator.user_should_be_at_the_rrsp_calculator_page()"},"name":"User should be at the rrsp calculator page","result":{"duration":23414700,"status":"passed"}},{"keyword":"And ","line":15,"match":{"location":"stepdefinitions.F1_RRSPCalculator.user_should_see_the_calculator_fields()"},"name":"User should see the Calculator fields","result":{"duration":1060765600,"status":"passed"}}]},{"start_timestamp":"2025-10-24T18:57:26.043Z","line":32,"id":"as-a-user-i-want-to-calculate-how-much-money-i-can-save-in-a-registered-retirement-savings;user-should-get-an-error-when-entering-rate-of-return-lower-than-1%-or-higher-than-1000%;;4","type":"scenario","keyword":"Scenario Outline","name":"User should get an error when entering rate of return lower than 1% or higher than 1000%","description":"","steps":[{"keyword":"When ","line":26,"match":{"location":"stepdefinitions.F1_RRSPCalculator.userInputsAnInvalidRateOfReturn(java.lang.String)","arguments":[{"val":"\"1001\"","offset":38}]},"name":"User inputs an invalid rate of return \"1001\"","result":{"duration":118077800,"status":"passed"}},{"keyword":"Then ","line":27,"match":{"location":"stepdefinitions.F1_RRSPCalculator.userShouldBeAbleToSeeTheMessage(java.lang.String)","arguments":[{"val":"\"Please select a rate between 1% and 1000%\"","offset":39}]},"name":"User should be able to see the message \"Please select a rate between 1% and 1000%\"","result":{"duration":38764300,"status":"passed"}}],"before":[{"match":{"location":"stepdefinitions.Hooks.init()"},"result":{"duration":831814900,"status":"passed"}}],"after":[{"match":{"location":"stepdefinitions.Hooks.tearDown()"},"result":{"duration":217053400,"status":"passed"}}],"tags":[{"name":"@RRSP"},{"name":"@RegressionTest"},{"name":"@IncorrectReturnRate"}]},{"line":7,"type":"background","keyword":"Background","name":"","description":"","steps":[{"keyword":"Given ","line":8,"match":{"location":"stepdefinitions.F1_RRSPCalculator.user_launches_the_application()"},"name":"User launches the application","result":{"duration":1129959400,"status":"passed"}},{"keyword":"And ","line":9,"match":{"location":"stepdefinitions.F1_RRSPCalculator.user_should_be_at_the_homepage()"},"name":"User should be at the homepage","result":{"duration":1038343500,"status":"passed"}},{"keyword":"And ","line":10,"match":{"location":"stepdefinitions.F1_RRSPCalculator.userAcceptsThePrivacySettings()"},"name":"User accepts the privacy settings","result":{"duration":138341700,"status":"passed"}},{"keyword":"And ","line":11,"match":{"location":"stepdefinitions.F1_RRSPCalculator.user_sees_the_investments_tab()"},"name":"User sees the Investments tab","result":{"duration":31172800,"status":"passed"}},{"keyword":"And ","line":12,"match":{"location":"stepdefinitions.F1_RRSPCalculator.user_hovers_over_investments_tab()"},"name":"User hovers over Investments tab","result":{"duration":143073500,"status":"passed"}},{"keyword":"And ","line":13,"match":{"location":"stepdefinitions.F1_RRSPCalculator.user_clicks_rrsp_calculator_link()"},"name":"User clicks RRSP Calculator link","result":{"duration":1143634500,"status":"passed"}},{"keyword":"And ","line":14,"match":{"location":"stepdefinitions.F1_RRSPCalculator.user_should_be_at_the_rrsp_calculator_page()"},"name":"User should be at the rrsp calculator page","result":{"duration":26577000,"status":"passed"}},{"keyword":"And ","line":15,"match":{"location":"stepdefinitions.F1_RRSPCalculator.user_should_see_the_calculator_fields()"},"name":"User should see the Calculator fields","result":{"duration":1064456900,"status":"passed"}}]},{"start_timestamp":"2025-10-24T18:57:32.062Z","line":33,"id":"as-a-user-i-want-to-calculate-how-much-money-i-can-save-in-a-registered-retirement-savings;user-should-get-an-error-when-entering-rate-of-return-lower-than-1%-or-higher-than-1000%;;5","type":"scenario","keyword":"Scenario Outline","name":"User should get an error when entering rate of return lower than 1% or higher than 1000%","description":"","steps":[{"keyword":"When ","line":26,"match":{"location":"stepdefinitions.F1_RRSPCalculator.userInputsAnInvalidRateOfReturn(java.lang.String)","arguments":[{"val":"\"1002\"","offset":38}]},"name":"User inputs an invalid rate of return \"1002\"","result":{"duration":132492400,"status":"passed"}},{"keyword":"Then ","line":27,"match":{"location":"stepdefinitions.F1_RRSPCalculator.userShouldBeAbleToSeeTheMessage(java.lang.String)","arguments":[{"val":"\"Please select a rate between 1% and 1000%\"","offset":39}]},"name":"User should be able to see the message \"Please select a rate between 1% and 1000%\"","result":{"duration":36749100,"status":"passed"}}],"before":[{"match":{"location":"stepdefinitions.Hooks.init()"},"result":{"duration":980330000,"status":"passed"}}],"after":[{"match":{"location":"stepdefinitions.Hooks.tearDown()"},"result":{"duration":220178600,"status":"passed"}}],"tags":[{"name":"@RRSP"},{"name":"@RegressionTest"},{"name":"@IncorrectReturnRate"}]},{"line":7,"type":"background","keyword":"Background","name":"","description":"","steps":[{"keyword":"Given ","line":8,"match":{"location":"stepdefinitions.F1_RRSPCalculator.user_launches_the_application()"},"name":"User launches the application","result":{"duration":1185924800,"status":"passed"}},{"keyword":"And ","line":9,"match":{"location":"stepdefinitions.F1_RRSPCalculator.user_should_be_at_the_homepage()"},"name":"User should be at the homepage","result":{"duration":1031735300,"status":"passed"}},{"keyword":"And ","line":10,"match":{"location":"stepdefinitions.F1_RRSPCalculator.userAcceptsThePrivacySettings()"},"name":"User accepts the privacy settings","result":{"duration":141017200,"status":"passed"}},{"keyword":"And ","line":11,"match":{"location":"stepdefinitions.F1_RRSPCalculator.user_sees_the_investments_tab()"},"name":"User sees the Investments tab","result":{"duration":26583100,"status":"passed"}},{"keyword":"And ","line":12,"match":{"location":"stepdefinitions.F1_RRSPCalculator.user_hovers_over_investments_tab()"},"name":"User hovers over Investments tab","result":{"duration":134676600,"status":"passed"}},{"keyword":"And ","line":13,"match":{"location":"stepdefinitions.F1_RRSPCalculator.user_clicks_rrsp_calculator_link()"},"name":"User clicks RRSP Calculator link","result":{"duration":1305086900,"status":"passed"}},{"keyword":"And ","line":14,"match":{"location":"stepdefinitions.F1_RRSPCalculator.user_should_be_at_the_rrsp_calculator_page()"},"name":"User should be at the rrsp calculator page","result":{"duration":42756300,"status":"passed"}},{"keyword":"And ","line":15,"match":{"location":"stepdefinitions.F1_RRSPCalculator.user_should_see_the_calculator_fields()"},"name":"User should see the Calculator fields","result":{"duration":1054322500,"status":"passed"}}]},{"start_timestamp":"2025-10-24T18:57:38.157Z","line":48,"id":"as-a-user-i-want-to-calculate-how-much-money-i-can-save-in-a-registered-retirement-savings;user-should-be-able-to-calculate-total-savings-given-and-shown-a-savings-tip-when;;2","type":"scenario","keyword":"Scenario Outline","name":"User should be able to calculate total savings given and shown a savings tip when","description":"  calculating with a frequency higher than Bi-weekly","steps":[{"keyword":"When ","line":38,"match":{"location":"stepdefinitions.F1_RRSPCalculator.user_inputs_the_years_to_retire(java.lang.String)","arguments":[{"val":"\"20\"","offset":22}]},"name":"User inputs the years \"20\" to retire","result":{"duration":1117760800,"status":"passed"}},{"keyword":"And ","line":39,"match":{"location":"stepdefinitions.F1_RRSPCalculator.user_inputs_the_ongoing_contribution_amount(java.lang.String)","arguments":[{"val":"\"300\"","offset":37}]},"name":"User inputs the ongoing contribution \"300\"","result":{"duration":1099779900,"status":"passed"}},{"keyword":"And ","line":40,"match":{"location":"stepdefinitions.F1_RRSPCalculator.user_selects_the_contribution_frequency(java.lang.String)","arguments":[{"val":"\"Monthly\"","offset":30}]},"name":"User selects the contribution \"Monthly\"","result":{"duration":1183545900,"status":"passed"}},{"keyword":"And ","line":41,"match":{"location":"stepdefinitions.F1_RRSPCalculator.user_inputs_the_rate_of_return(java.lang.String)","arguments":[{"val":"\"5\"","offset":16}]},"name":"User inputs the \"5\" of return","result":{"duration":1119675100,"status":"passed"}},{"keyword":"And ","line":42,"match":{"location":"stepdefinitions.F1_RRSPCalculator.userClicksCalculateButton()"},"name":"User clicks calculate button","result":{"duration":1170578100,"status":"passed"}},{"keyword":"Then ","line":43,"match":{"location":"stepdefinitions.F1_RRSPCalculator.userShouldSeeTheTotal(java.lang.String)","arguments":[{"val":"\"$123,310.10\"","offset":26}]},"name":"User should see the total \"$123,310.10\"","result":{"duration":39835600,"status":"passed"}},{"keyword":"Then ","line":44,"match":{"location":"stepdefinitions.F1_RRSPCalculator.userShouldSeeATipWithPotentialSavingsAndRecommendedContributionAmount(java.lang.String,java.lang.String)","arguments":[{"val":"\"$10,512\"","offset":45},{"val":"\"$150\"","offset":91}]},"name":"User should see a tip with potential savings \"$10,512\" and recommended contribution amount \"$150\"","result":{"duration":37068400,"status":"passed"}}],"before":[{"match":{"location":"stepdefinitions.Hooks.init()"},"result":{"duration":889371600,"status":"passed"}}],"after":[{"match":{"location":"stepdefinitions.Hooks.tearDown()"},"result":{"duration":245648500,"status":"passed"}}],"tags":[{"name":"@RRSP"},{"name":"@RegressionTest"},{"name":"@TotalSavings"}]},{"line":7,"type":"background","keyword":"Background","name":"","description":"","steps":[{"keyword":"Given ","line":8,"match":{"location":"stepdefinitions.F1_RRSPCalculator.user_launches_the_application()"},"name":"User launches the application","result":{"duration":1170587400,"status":"passed"}},{"keyword":"And ","line":9,"match":{"location":"stepdefinitions.F1_RRSPCalculator.user_should_be_at_the_homepage()"},"name":"User should be at the homepage","result":{"duration":1038599600,"status":"passed"}},{"keyword":"And ","line":10,"match":{"location":"stepdefinitions.F1_RRSPCalculator.userAcceptsThePrivacySettings()"},"name":"User accepts the privacy settings","result":{"duration":153514900,"status":"passed"}},{"keyword":"And ","line":11,"match":{"location":"stepdefinitions.F1_RRSPCalculator.user_sees_the_investments_tab()"},"name":"User sees the Investments tab","result":{"duration":22821800,"status":"passed"}},{"keyword":"And ","line":12,"match":{"location":"stepdefinitions.F1_RRSPCalculator.user_hovers_over_investments_tab()"},"name":"User hovers over Investments tab","result":{"duration":134915900,"status":"passed"}},{"keyword":"And ","line":13,"match":{"location":"stepdefinitions.F1_RRSPCalculator.user_clicks_rrsp_calculator_link()"},"name":"User clicks RRSP Calculator link","result":{"duration":1244244200,"status":"passed"}},{"keyword":"And ","line":14,"match":{"location":"stepdefinitions.F1_RRSPCalculator.user_should_be_at_the_rrsp_calculator_page()"},"name":"User should be at the rrsp calculator page","result":{"duration":27876500,"status":"passed"}},{"keyword":"And ","line":15,"match":{"location":"stepdefinitions.F1_RRSPCalculator.user_should_see_the_calculator_fields()"},"name":"User should see the Calculator fields","result":{"duration":1058233500,"status":"passed"}}]},{"start_timestamp":"2025-10-24T18:57:49.990Z","line":49,"id":"as-a-user-i-want-to-calculate-how-much-money-i-can-save-in-a-registered-retirement-savings;user-should-be-able-to-calculate-total-savings-given-and-shown-a-savings-tip-when;;3","type":"scenario","keyword":"Scenario Outline","name":"User should be able to calculate total savings given and shown a savings tip when","description":"  calculating with a frequency higher than Bi-weekly","steps":[{"keyword":"When ","line":38,"match":{"location":"stepdefinitions.F1_RRSPCalculator.user_inputs_the_years_to_retire(java.lang.String)","arguments":[{"val":"\"1\"","offset":22}]},"name":"User inputs the years \"1\" to retire","result":{"duration":1125783600,"status":"passed"}},{"keyword":"And ","line":39,"match":{"location":"stepdefinitions.F1_RRSPCalculator.user_inputs_the_ongoing_contribution_amount(java.lang.String)","arguments":[{"val":"\"25\"","offset":37}]},"name":"User inputs the ongoing contribution \"25\"","result":{"duration":1107054500,"status":"passed"}},{"keyword":"And ","line":40,"match":{"location":"stepdefinitions.F1_RRSPCalculator.user_selects_the_contribution_frequency(java.lang.String)","arguments":[{"val":"\"Monthly\"","offset":30}]},"name":"User selects the contribution \"Monthly\"","result":{"duration":1152511300,"status":"passed"}},{"keyword":"And ","line":41,"match":{"location":"stepdefinitions.F1_RRSPCalculator.user_inputs_the_rate_of_return(java.lang.String)","arguments":[{"val":"\"1\"","offset":16}]},"name":"User inputs the \"1\" of return","result":{"duration":1126310000,"status":"passed"}},{"keyword":"And ","line":42,"match":{"location":"stepdefinitions.F1_RRSPCalculator.userClicksCalculateButton()"},"name":"User clicks calculate button","result":{"duration":1148650600,"status":"passed"}},{"keyword":"Then ","line":43,"match":{"location":"stepdefinitions.F1_RRSPCalculator.userShouldSeeTheTotal(java.lang.String)","arguments":[{"val":"\"$301.38\"","offset":26}]},"name":"User should see the total \"$301.38\"","result":{"duration":35164400,"status":"passed"}},{"keyword":"Then ","line":44,"match":{"location":"stepdefinitions.F1_RRSPCalculator.userShouldSeeATipWithPotentialSavingsAndRecommendedContributionAmount(java.lang.String,java.lang.String)","arguments":[{"val":"\"$25\"","offset":45},{"val":"\"$13\"","offset":87}]},"name":"User should see a tip with potential savings \"$25\" and recommended contribution amount \"$13\"","result":{"duration":36658900,"status":"passed"}}],"before":[{"match":{"location":"stepdefinitions.Hooks.init()"},"result":{"duration":862329300,"status":"passed"}}],"after":[{"match":{"location":"stepdefinitions.Hooks.tearDown()"},"result":{"duration":266077500,"status":"passed"}}],"tags":[{"name":"@RRSP"},{"name":"@RegressionTest"},{"name":"@TotalSavings"}]},{"line":7,"type":"background","keyword":"Background","name":"","description":"","steps":[{"keyword":"Given ","line":8,"match":{"location":"stepdefinitions.F1_RRSPCalculator.user_launches_the_application()"},"name":"User launches the application","result":{"duration":1227679900,"status":"passed"}},{"keyword":"And ","line":9,"match":{"location":"stepdefinitions.F1_RRSPCalculator.user_should_be_at_the_homepage()"},"name":"User should be at the homepage","result":{"duration":1042271000,"status":"passed"}},{"keyword":"And ","line":10,"match":{"location":"stepdefinitions.F1_RRSPCalculator.userAcceptsThePrivacySettings()"},"name":"User accepts the privacy settings","result":{"duration":135506700,"status":"passed"}},{"keyword":"And ","line":11,"match":{"location":"stepdefinitions.F1_RRSPCalculator.user_sees_the_investments_tab()"},"name":"User sees the Investments tab","result":{"duration":23907500,"status":"passed"}},{"keyword":"And ","line":12,"match":{"location":"stepdefinitions.F1_RRSPCalculator.user_hovers_over_investments_tab()"},"name":"User hovers over Investments tab","result":{"duration":139083200,"status":"passed"}},{"keyword":"And ","line":13,"match":{"location":"stepdefinitions.F1_RRSPCalculator.user_clicks_rrsp_calculator_link()"},"name":"User clicks RRSP Calculator link","result":{"duration":1198054000,"status":"passed"}},{"keyword":"And ","line":14,"match":{"location":"stepdefinitions.F1_RRSPCalculator.user_should_be_at_the_rrsp_calculator_page()"},"name":"User should be at the rrsp calculator page","result":{"duration":25324500,"status":"passed"}},{"keyword":"And ","line":15,"match":{"location":"stepdefinitions.F1_RRSPCalculator.user_should_see_the_calculator_fields()"},"name":"User should see the Calculator fields","result":{"duration":1057814900,"status":"passed"}}]},{"start_timestamp":"2025-10-24T18:58:01.720Z","line":50,"id":"as-a-user-i-want-to-calculate-how-much-money-i-can-save-in-a-registered-retirement-savings;user-should-be-able-to-calculate-total-savings-given-and-shown-a-savings-tip-when;;4","type":"scenario","keyword":"Scenario Outline","name":"User should be able to calculate total savings given and shown a savings tip when","description":"  calculating with a frequency higher than Bi-weekly","steps":[{"keyword":"When ","line":38,"match":{"location":"stepdefinitions.F1_RRSPCalculator.user_inputs_the_years_to_retire(java.lang.String)","arguments":[{"val":"\"50\"","offset":22}]},"name":"User inputs the years \"50\" to retire","result":{"duration":1104243000,"status":"passed"}},{"keyword":"And ","line":39,"match":{"location":"stepdefinitions.F1_RRSPCalculator.user_inputs_the_ongoing_contribution_amount(java.lang.String)","arguments":[{"val":"\"25\"","offset":37}]},"name":"User inputs the ongoing contribution \"25\"","result":{"duration":1117569900,"status":"passed"}},{"keyword":"And ","line":40,"match":{"location":"stepdefinitions.F1_RRSPCalculator.user_selects_the_contribution_frequency(java.lang.String)","arguments":[{"val":"\"Quarterly\"","offset":30}]},"name":"User selects the contribution \"Quarterly\"","result":{"duration":1204768900,"status":"passed"}},{"keyword":"And ","line":41,"match":{"location":"stepdefinitions.F1_RRSPCalculator.user_inputs_the_rate_of_return(java.lang.String)","arguments":[{"val":"\"1\"","offset":16}]},"name":"User inputs the \"1\" of return","result":{"duration":1105596400,"status":"passed"}},{"keyword":"And ","line":42,"match":{"location":"stepdefinitions.F1_RRSPCalculator.userClicksCalculateButton()"},"name":"User clicks calculate button","result":{"duration":1158776700,"status":"passed"}},{"keyword":"Then ","line":43,"match":{"location":"stepdefinitions.F1_RRSPCalculator.userShouldSeeTheTotal(java.lang.String)","arguments":[{"val":"\"$6,476.93\"","offset":26}]},"name":"User should see the total \"$6,476.93\"","result":{"duration":39152700,"status":"passed"}},{"keyword":"Then ","line":44,"match":{"location":"stepdefinitions.F1_RRSPCalculator.userShouldSeeATipWithPotentialSavingsAndRecommendedContributionAmount(java.lang.String,java.lang.String)","arguments":[{"val":"\"$549\"","offset":45},{"val":"\"$4\"","offset":88}]},"name":"User should see a tip with potential savings \"$549\" and recommended contribution amount \"$4\"","result":{"duration":38623200,"status":"passed"}}],"before":[{"match":{"location":"stepdefinitions.Hooks.init()"},"result":{"duration":842262500,"status":"passed"}}],"after":[{"match":{"location":"stepdefinitions.Hooks.tearDown()"},"result":{"duration":265328800,"status":"passed"}}],"tags":[{"name":"@RRSP"},{"name":"@RegressionTest"},{"name":"@TotalSavings"}]}],"tags":[{"name":"@RRSP","type":"Tag","location":{"line":3,"column":1}},{"name":"@RegressionTest","type":"Tag","location":{"line":3,"column":7}}]},{"line":4,"uri":"file:src/test/resources/features/F2_RentBuyCalculator.feature","id":"as-a-user-i-want-to-calculate-how-much-money-i-can-save-in-a-registered-retirement-savings","keyword":"Feature","name":"As a user I want to calculate how much money I can save in a registered retirement savings","description":"  plan so that reach my retirement goals","elements":[{"line":7,"type":"background","keyword":"Background","name":"","description":"","steps":[{"keyword":"Given ","line":8,"match":{"location":"stepdefinitions.F1_RRSPCalculator.user_launches_the_application()"},"name":"User launches the application","result":{"duration":1133892100,"status":"passed"}},{"keyword":"And ","line":9,"match":{"location":"stepdefinitions.F1_RRSPCalculator.user_should_be_at_the_homepage()"},"name":"User should be at the homepage","result":{"duration":1030681500,"status":"passed"}},{"keyword":"And ","line":10,"match":{"location":"stepdefinitions.F1_RRSPCalculator.userAcceptsThePrivacySettings()"},"name":"User accepts the privacy settings","result":{"duration":146109600,"status":"passed"}},{"keyword":"And ","line":11,"match":{"location":"stepdefinitions.F2_RentBuyCalculator.user_sees_the_mortgages_tab()"},"name":"User sees the Mortgages tab","result":{"duration":37371800,"status":"passed"}},{"keyword":"And ","line":12,"match":{"location":"stepdefinitions.F2_RentBuyCalculator.user_hovers_over_mortgages_tab()"},"name":"User hovers over Mortgages tab","result":{"duration":142416300,"status":"passed"}},{"keyword":"And ","line":13,"match":{"location":"stepdefinitions.F2_RentBuyCalculator.user_clicks_rent_vs_buy_calculator()"},"name":"User clicks Rent vs Buy Calculator","result":{"duration":1549788300,"status":"passed"}},{"keyword":"And ","line":14,"match":{"location":"stepdefinitions.F2_RentBuyCalculator.user_should_be_at_the_rent_vs_buy_calculator_page()"},"name":"User should be at the Rent vs Buy Calculator page","result":{"duration":44288800,"status":"passed"}},{"keyword":"And ","line":15,"match":{"location":"stepdefinitions.F2_RentBuyCalculator.user_should_see_the_calculator_fields()"},"name":"User should see the calculator fields","result":{"duration":20598600,"status":"passed"}}]},{"start_timestamp":"2025-10-24T18:58:13.458Z","line":18,"id":"as-a-user-i-want-to-calculate-how-much-money-i-can-save-in-a-registered-retirement-savings;user-should-be-able-to-click-on-the-amortization-period-and-get-a-clear-message-of-what-it-means","type":"scenario","keyword":"Scenario","name":"User should be able to click on the amortization period and get a clear message of what it means","description":"","steps":[{"keyword":"When ","line":19,"match":{"location":"stepdefinitions.F2_RentBuyCalculator.userClicksTheAmortizationPeriodTooltip()"},"name":"User clicks the amortization period tooltip","result":{"duration":189499900,"status":"passed"}},{"keyword":"Then ","line":20,"match":{"location":"stepdefinitions.F2_RentBuyCalculator.userShouldBeAbleToSee(java.lang.String)","arguments":[{"val":"\"Most people choose a 25-year amortization period\"","offset":27}]},"name":"User should be able to see \"Most people choose a 25-year amortization period\" in the period message","result":{"duration":28620300,"status":"passed"}}],"before":[{"match":{"location":"stepdefinitions.Hooks.init()"},"result":{"duration":870238000,"status":"passed"}}],"after":[{"match":{"location":"stepdefinitions.Hooks.tearDown()"},"result":{"duration":211583700,"status":"passed"}}],"tags":[{"name":"@RentBuyCalculator"},{"name":"@RegressionTest"},{"name":"@AmortizationTooltip"}]},{"line":7,"type":"background","keyword":"Background","name":"","description":"","steps":[{"keyword":"Given ","line":8,"match":{"location":"stepdefinitions.F1_RRSPCalculator.user_launches_the_application()"},"name":"User launches the application","result":{"duration":1408844200,"status":"passed"}},{"keyword":"And ","line":9,"match":{"location":"stepdefinitions.F1_RRSPCalculator.user_should_be_at_the_homepage()"},"name":"User should be at the homepage","result":{"duration":1039993100,"status":"passed"}},{"keyword":"And ","line":10,"match":{"location":"stepdefinitions.F1_RRSPCalculator.userAcceptsThePrivacySettings()"},"name":"User accepts the privacy settings","result":{"duration":364000000,"status":"passed"}},{"keyword":"And ","line":11,"match":{"location":"stepdefinitions.F2_RentBuyCalculator.user_sees_the_mortgages_tab()"},"name":"User sees the Mortgages tab","result":{"duration":26747500,"status":"passed"}},{"keyword":"And ","line":12,"match":{"location":"stepdefinitions.F2_RentBuyCalculator.user_hovers_over_mortgages_tab()"},"name":"User hovers over Mortgages tab","result":{"duration":130032400,"status":"passed"}},{"keyword":"And ","line":13,"match":{"location":"stepdefinitions.F2_RentBuyCalculator.user_clicks_rent_vs_buy_calculator()"},"name":"User clicks Rent vs Buy Calculator","result":{"duration":1610957800,"status":"passed"}},{"keyword":"And ","line":14,"match":{"location":"stepdefinitions.F2_RentBuyCalculator.user_should_be_at_the_rent_vs_buy_calculator_page()"},"name":"User should be at the Rent vs Buy Calculator page","result":{"duration":56719700,"status":"passed"}},{"keyword":"And ","line":15,"match":{"location":"stepdefinitions.F2_RentBuyCalculator.user_should_see_the_calculator_fields()"},"name":"User should see the calculator fields","result":{"duration":20481100,"status":"passed"}}]},{"start_timestamp":"2025-10-24T18:58:18.871Z","line":23,"id":"as-a-user-i-want-to-calculate-how-much-money-i-can-save-in-a-registered-retirement-savings;user-should-be-able-to-click-on-the-down-payment-tooltip-and-get-a-clear-message-of-what-it-means","type":"scenario","keyword":"Scenario","name":"User should be able to click on the down payment tooltip and get a clear message of what it means","description":"","steps":[{"keyword":"When ","line":24,"match":{"location":"stepdefinitions.F2_RentBuyCalculator.userClicksTheDownPaymentTooltip()"},"name":"User clicks the down payment tooltip","result":{"duration":146226300,"status":"passed"}},{"keyword":"Then ","line":25,"match":{"location":"stepdefinitions.F2_RentBuyCalculator.userShouldBeAbleToSeeInTheDownPayment(java.lang.String)","arguments":[{"val":"\"In order to be approved for a mortgage, you will need at least 5% of the purchase price\"","offset":27}]},"name":"User should be able to see \"In order to be approved for a mortgage, you will need at least 5% of the purchase price\" in the down payment","result":{"duration":81718500,"status":"passed"}}],"before":[{"match":{"location":"stepdefinitions.Hooks.init()"},"result":{"duration":2797078900,"status":"passed"}}],"after":[{"match":{"location":"stepdefinitions.Hooks.tearDown()"},"result":{"duration":208753700,"status":"passed"}}],"tags":[{"name":"@RentBuyCalculator"},{"name":"@RegressionTest"},{"name":"@DownPaymentTooltip"}]},{"line":7,"type":"background","keyword":"Background","name":"","description":"","steps":[{"keyword":"Given ","line":8,"match":{"location":"stepdefinitions.F1_RRSPCalculator.user_launches_the_application()"},"name":"User launches the application","result":{"duration":1370049300,"status":"passed"}},{"keyword":"And ","line":9,"match":{"location":"stepdefinitions.F1_RRSPCalculator.user_should_be_at_the_homepage()"},"name":"User should be at the homepage","result":{"duration":1034652500,"status":"passed"}},{"keyword":"And ","line":10,"match":{"location":"stepdefinitions.F1_RRSPCalculator.userAcceptsThePrivacySettings()"},"name":"User accepts the privacy settings","result":{"duration":176713200,"status":"passed"}},{"keyword":"And ","line":11,"match":{"location":"stepdefinitions.F2_RentBuyCalculator.user_sees_the_mortgages_tab()"},"name":"User sees the Mortgages tab","result":{"duration":44174500,"status":"passed"}},{"keyword":"And ","line":12,"match":{"location":"stepdefinitions.F2_RentBuyCalculator.user_hovers_over_mortgages_tab()"},"name":"User hovers over Mortgages tab","result":{"duration":133184500,"status":"passed"}},{"keyword":"And ","line":13,"match":{"location":"stepdefinitions.F2_RentBuyCalculator.user_clicks_rent_vs_buy_calculator()"},"name":"User clicks Rent vs Buy Calculator","result":{"duration":1919728500,"status":"passed"}},{"keyword":"And ","line":14,"match":{"location":"stepdefinitions.F2_RentBuyCalculator.user_should_be_at_the_rent_vs_buy_calculator_page()"},"name":"User should be at the Rent vs Buy Calculator page","result":{"duration":50430200,"status":"passed"}},{"keyword":"And ","line":15,"match":{"location":"stepdefinitions.F2_RentBuyCalculator.user_should_see_the_calculator_fields()"},"name":"User should see the calculator fields","result":{"duration":15680500,"status":"passed"}}]},{"start_timestamp":"2025-10-24T18:58:26.770Z","line":34,"id":"as-a-user-i-want-to-calculate-how-much-money-i-can-save-in-a-registered-retirement-savings;user-should-be-able-to-see-an-error-message-if-monthly-rent-is-not-provided;;2","type":"scenario","keyword":"Scenario Outline","name":"User should be able to see an error message if monthly rent is not provided","description":"","steps":[{"keyword":"When ","line":29,"match":{"location":"stepdefinitions.F2_RentBuyCalculator.user_inputs_monthly_rent(java.lang.String)","arguments":[{"val":"\"0\"","offset":25}]},"name":"User inputs monthly rent \"0\"","result":{"duration":65329100,"status":"passed"}},{"keyword":"Then ","line":30,"match":{"location":"stepdefinitions.F2_RentBuyCalculator.userShouldNotTBeAbleToClickOnTheCalculateButtonAndItShouldBeDisabled()"},"name":"User shouldn't be able to click on the calculate button and it should be disabled","result":{"duration":258772800,"status":"passed"}},{"keyword":"Then ","line":31,"match":{"location":"stepdefinitions.F2_RentBuyCalculator.userShouldSeeAnErrorMessage(java.lang.String)","arguments":[{"val":"\"Please enter your monthly rent.\"","offset":33}]},"name":"User should see an error message \"Please enter your monthly rent.\"","result":{"duration":23279800,"status":"passed"}}],"before":[{"match":{"location":"stepdefinitions.Hooks.init()"},"result":{"duration":994004800,"status":"passed"}}],"after":[{"match":{"location":"stepdefinitions.Hooks.tearDown()"},"result":{"duration":192538600,"status":"passed"}}],"tags":[{"name":"@RentBuyCalculator"},{"name":"@RegressionTest"},{"name":"@RentNotProvided"}]},{"line":7,"type":"background","keyword":"Background","name":"","description":"","steps":[{"keyword":"Given ","line":8,"match":{"location":"stepdefinitions.F1_RRSPCalculator.user_launches_the_application()"},"name":"User launches the application","result":{"duration":1550914200,"status":"passed"}},{"keyword":"And ","line":9,"match":{"location":"stepdefinitions.F1_RRSPCalculator.user_should_be_at_the_homepage()"},"name":"User should be at the homepage","result":{"duration":1030724200,"status":"passed"}},{"keyword":"And ","line":10,"match":{"location":"stepdefinitions.F1_RRSPCalculator.userAcceptsThePrivacySettings()"},"name":"User accepts the privacy settings","result":{"duration":178470300,"status":"passed"}},{"keyword":"And ","line":11,"match":{"location":"stepdefinitions.F2_RentBuyCalculator.user_sees_the_mortgages_tab()"},"name":"User sees the Mortgages tab","result":{"duration":25281600,"status":"passed"}},{"keyword":"And ","line":12,"match":{"location":"stepdefinitions.F2_RentBuyCalculator.user_hovers_over_mortgages_tab()"},"name":"User hovers over Mortgages tab","result":{"duration":146162700,"status":"passed"}},{"keyword":"And ","line":13,"match":{"location":"stepdefinitions.F2_RentBuyCalculator.user_clicks_rent_vs_buy_calculator()"},"name":"User clicks Rent vs Buy Calculator","result":{"duration":1655704400,"status":"passed"}},{"keyword":"And ","line":14,"match":{"location":"stepdefinitions.F2_RentBuyCalculator.user_should_be_at_the_rent_vs_buy_calculator_page()"},"name":"User should be at the Rent vs Buy Calculator page","result":{"duration":94256700,"status":"passed"}},{"keyword":"And ","line":15,"match":{"location":"stepdefinitions.F2_RentBuyCalculator.user_should_see_the_calculator_fields()"},"name":"User should see the calculator fields","result":{"duration":29275400,"status":"passed"}}]},{"start_timestamp":"2025-10-24T18:58:33.057Z","line":35,"id":"as-a-user-i-want-to-calculate-how-much-money-i-can-save-in-a-registered-retirement-savings;user-should-be-able-to-see-an-error-message-if-monthly-rent-is-not-provided;;3","type":"scenario","keyword":"Scenario Outline","name":"User should be able to see an error message if monthly rent is not provided","description":"","steps":[{"keyword":"When ","line":29,"match":{"location":"stepdefinitions.F2_RentBuyCalculator.user_inputs_monthly_rent(java.lang.String)","arguments":[{"val":"\"\"","offset":25}]},"name":"User inputs monthly rent \"\"","result":{"duration":105924600,"status":"passed"}},{"keyword":"Then ","line":30,"match":{"location":"stepdefinitions.F2_RentBuyCalculator.userShouldNotTBeAbleToClickOnTheCalculateButtonAndItShouldBeDisabled()"},"name":"User shouldn't be able to click on the calculate button and it should be disabled","result":{"duration":346067800,"status":"passed"}},{"keyword":"Then ","line":31,"match":{"location":"stepdefinitions.F2_RentBuyCalculator.userShouldSeeAnErrorMessage(java.lang.String)","arguments":[{"val":"\"Please enter your monthly rent.\"","offset":33}]},"name":"User should see an error message \"Please enter your monthly rent.\"","result":{"duration":36430400,"status":"passed"}}],"before":[{"match":{"location":"stepdefinitions.Hooks.init()"},"result":{"duration":932741900,"status":"passed"}}],"after":[{"match":{"location":"stepdefinitions.Hooks.tearDown()"},"result":{"duration":207468100,"status":"passed"}}],"tags":[{"name":"@RentBuyCalculator"},{"name":"@RegressionTest"},{"name":"@RentNotProvided"}]},{"line":7,"type":"background","keyword":"Background","name":"","description":"","steps":[{"keyword":"Given ","line":8,"match":{"location":"stepdefinitions.F1_RRSPCalculator.user_launches_the_application()"},"name":"User launches the application","result":{"duration":1850246500,"status":"passed"}},{"keyword":"And ","line":9,"match":{"location":"stepdefinitions.F1_RRSPCalculator.user_should_be_at_the_homepage()"},"name":"User should be at the homepage","result":{"duration":1039982800,"status":"passed"}},{"keyword":"And ","line":10,"match":{"location":"stepdefinitions.F1_RRSPCalculator.userAcceptsThePrivacySettings()"},"name":"User accepts the privacy settings","result":{"duration":255108400,"status":"passed"}},{"keyword":"And ","line":11,"match":{"location":"stepdefinitions.F2_RentBuyCalculator.user_sees_the_mortgages_tab()"},"name":"User sees the Mortgages tab","result":{"duration":57938200,"status":"passed"}},{"keyword":"And ","line":12,"match":{"location":"stepdefinitions.F2_RentBuyCalculator.user_hovers_over_mortgages_tab()"},"name":"User hovers over Mortgages tab","result":{"duration":147322600,"status":"passed"}},{"keyword":"And ","line":13,"match":{"location":"stepdefinitions.F2_RentBuyCalculator.user_clicks_rent_vs_buy_calculator()"},"name":"User clicks Rent vs Buy Calculator","result":{"duration":2192334400,"status":"passed"}},{"keyword":"And ","line":14,"match":{"location":"stepdefinitions.F2_RentBuyCalculator.user_should_be_at_the_rent_vs_buy_calculator_page()"},"name":"User should be at the Rent vs Buy Calculator page","result":{"duration":96816600,"status":"passed"}},{"keyword":"And ","line":15,"match":{"location":"stepdefinitions.F2_RentBuyCalculator.user_should_see_the_calculator_fields()"},"name":"User should see the calculator fields","result":{"duration":55695900,"status":"passed"}}]},{"start_timestamp":"2025-10-24T18:58:39.407Z","line":50,"id":"as-a-user-i-want-to-calculate-how-much-money-i-can-save-in-a-registered-retirement-savings;user-should-be-able-to-see-the-mortgage-(loan)-amount-when-selecting-5%--10%-and-20%-down-payment-for-a;;2","type":"scenario","keyword":"Scenario Outline","name":"User should be able to see the mortgage (loan) amount when selecting 5%, 10% and 20% down payment for a","description":"  given purchase price.","steps":[{"keyword":"When ","line":40,"match":{"location":"stepdefinitions.F2_RentBuyCalculator.user_inputs_monthly_rent(java.lang.String)","arguments":[{"val":"\"800\"","offset":25}]},"name":"User inputs monthly rent \"800\"","result":{"duration":187017200,"status":"passed"}},{"keyword":"And ","line":41,"match":{"location":"stepdefinitions.F2_RentBuyCalculator.user_inputs_interest_rate_percent(java.lang.String)","arguments":[{"val":"\"4.590\"","offset":26}]},"name":"User inputs interest rate \"4.590\" percent","result":{"duration":280944000,"status":"passed"}},{"keyword":"And ","line":42,"match":{"location":"stepdefinitions.F2_RentBuyCalculator.user_selects_the_amortization_period(java.lang.String)","arguments":[{"val":"\"30 years\"","offset":30}]},"name":"User selects the amortization \"30 years\" period","result":{"duration":176742800,"status":"passed"}},{"keyword":"And ","line":43,"match":{"location":"stepdefinitions.F2_RentBuyCalculator.user_selects_the_down_payment_percentage(java.lang.String)","arguments":[{"val":"\"5%\"","offset":30}]},"name":"User selects the down payment \"5%\" percentage","result":{"duration":167447900,"status":"passed"}},{"keyword":"And ","line":44,"match":{"location":"stepdefinitions.F2_RentBuyCalculator.user_clicks_calculate_button_in_rent_vs_buy_calculator()"},"name":"User clicks calculate button in rent vs buy calculator","result":{"duration":296169500,"status":"passed"}},{"keyword":"Then ","line":45,"match":{"location":"stepdefinitions.F2_RentBuyCalculator.user_should_be_able_to_see_cards_for_and_down_payment()"},"name":"User should be able to see 3 cards for 5%, 10% and 20% down payment","result":{"duration":740608600,"status":"passed"}},{"keyword":"And ","line":46,"match":{"location":"stepdefinitions.F2_RentBuyCalculator.userShouldBeAbleToSeeTheTotalMortgage(java.lang.String,java.lang.String,java.lang.String)","arguments":[{"val":"\"$158,935\"","offset":46},{"val":"\"$169,230\"","offset":57},{"val":"\"$196,285\"","offset":68}]},"name":"User should be able to see the total mortgage \"$158,935\" \"$169,230\" \"$196,285\"","result":{"duration":143477700,"status":"passed"}}],"before":[{"match":{"location":"stepdefinitions.Hooks.init()"},"result":{"duration":861271500,"status":"passed"}}],"after":[{"match":{"location":"stepdefinitions.Hooks.tearDown()"},"result":{"duration":246519000,"status":"passed"}}],"tags":[{"name":"@RentBuyCalculator"},{"name":"@RegressionTest"},{"name":"@MortgageRentResult"}]},{"line":7,"type":"background","keyword":"Background","name":"","description":"","steps":[{"keyword":"Given ","line":8,"match":{"location":"stepdefinitions.F1_RRSPCalculator.user_launches_the_application()"},"name":"User launches the application","result":{"duration":1824611600,"status":"passed"}},{"keyword":"And ","line":9,"match":{"location":"stepdefinitions.F1_RRSPCalculator.user_should_be_at_the_homepage()"},"name":"User should be at the homepage","result":{"duration":1047404900,"status":"passed"}},{"keyword":"And ","line":10,"match":{"location":"stepdefinitions.F1_RRSPCalculator.userAcceptsThePrivacySettings()"},"name":"User accepts the privacy settings","result":{"duration":283405400,"status":"passed"}},{"keyword":"And ","line":11,"match":{"location":"stepdefinitions.F2_RentBuyCalculator.user_sees_the_mortgages_tab()"},"name":"User sees the Mortgages tab","result":{"duration":36615800,"status":"passed"}},{"keyword":"And ","line":12,"match":{"location":"stepdefinitions.F2_RentBuyCalculator.user_hovers_over_mortgages_tab()"},"name":"User hovers over Mortgages tab","result":{"duration":144703200,"status":"passed"}},{"keyword":"And ","line":13,"match":{"location":"stepdefinitions.F2_RentBuyCalculator.user_clicks_rent_vs_buy_calculator()"},"name":"User clicks Rent vs Buy Calculator","result":{"duration":2342433500,"status":"passed"}},{"keyword":"And ","line":14,"match":{"location":"stepdefinitions.F2_RentBuyCalculator.user_should_be_at_the_rent_vs_buy_calculator_page()"},"name":"User should be at the Rent vs Buy Calculator page","result":{"duration":94702400,"status":"passed"}},{"keyword":"And ","line":15,"match":{"location":"stepdefinitions.F2_RentBuyCalculator.user_should_see_the_calculator_fields()"},"name":"User should see the calculator fields","result":{"duration":31032000,"status":"passed"}}]},{"start_timestamp":"2025-10-24T18:58:48.208Z","line":51,"id":"as-a-user-i-want-to-calculate-how-much-money-i-can-save-in-a-registered-retirement-savings;user-should-be-able-to-see-the-mortgage-(loan)-amount-when-selecting-5%--10%-and-20%-down-payment-for-a;;3","type":"scenario","keyword":"Scenario Outline","name":"User should be able to see the mortgage (loan) amount when selecting 5%, 10% and 20% down payment for a","description":"  given purchase price.","steps":[{"keyword":"When ","line":40,"match":{"location":"stepdefinitions.F2_RentBuyCalculator.user_inputs_monthly_rent(java.lang.String)","arguments":[{"val":"\"1200\"","offset":25}]},"name":"User inputs monthly rent \"1200\"","result":{"duration":95665300,"status":"passed"}},{"keyword":"And ","line":41,"match":{"location":"stepdefinitions.F2_RentBuyCalculator.user_inputs_interest_rate_percent(java.lang.String)","arguments":[{"val":"\"5\"","offset":26}]},"name":"User inputs interest rate \"5\" percent","result":{"duration":358249700,"status":"passed"}},{"keyword":"And ","line":42,"match":{"location":"stepdefinitions.F2_RentBuyCalculator.user_selects_the_amortization_period(java.lang.String)","arguments":[{"val":"\"20 years\"","offset":30}]},"name":"User selects the amortization \"20 years\" period","result":{"duration":293502300,"status":"passed"}},{"keyword":"And ","line":43,"match":{"location":"stepdefinitions.F2_RentBuyCalculator.user_selects_the_down_payment_percentage(java.lang.String)","arguments":[{"val":"\"10%\"","offset":30}]},"name":"User selects the down payment \"10%\" percentage","result":{"duration":234694500,"status":"passed"}},{"keyword":"And ","line":44,"match":{"location":"stepdefinitions.F2_RentBuyCalculator.user_clicks_calculate_button_in_rent_vs_buy_calculator()"},"name":"User clicks calculate button in rent vs buy calculator","result":{"duration":221561900,"status":"passed"}},{"keyword":"Then ","line":45,"match":{"location":"stepdefinitions.F2_RentBuyCalculator.user_should_be_able_to_see_cards_for_and_down_payment()"},"name":"User should be able to see 3 cards for 5%, 10% and 20% down payment","result":{"duration":802602000,"status":"passed"}},{"keyword":"And ","line":46,"match":{"location":"stepdefinitions.F2_RentBuyCalculator.userShouldBeAbleToSeeTheTotalMortgage(java.lang.String,java.lang.String,java.lang.String)","arguments":[{"val":"\"$184,832\"","offset":46},{"val":"\"$196,803\"","offset":57},{"val":"\"$228,267\"","offset":68}]},"name":"User should be able to see the total mortgage \"$184,832\" \"$196,803\" \"$228,267\"","result":{"duration":148080200,"status":"passed"}}],"before":[{"match":{"location":"stepdefinitions.Hooks.init()"},"result":{"duration":1086931800,"status":"passed"}}],"after":[{"match":{"location":"stepdefinitions.Hooks.tearDown()"},"result":{"duration":209685100,"status":"passed"}}],"tags":[{"name":"@RentBuyCalculator"},{"name":"@RegressionTest"},{"name":"@MortgageRentResult"}]},{"line":7,"type":"background","keyword":"Background","name":"","description":"","steps":[{"keyword":"Given ","line":8,"match":{"location":"stepdefinitions.F1_RRSPCalculator.user_launches_the_application()"},"name":"User launches the application","result":{"duration":1392325400,"status":"passed"}},{"keyword":"And ","line":9,"match":{"location":"stepdefinitions.F1_RRSPCalculator.user_should_be_at_the_homepage()"},"name":"User should be at the homepage","result":{"duration":1043542200,"status":"passed"}},{"keyword":"And ","line":10,"match":{"location":"stepdefinitions.F1_RRSPCalculator.userAcceptsThePrivacySettings()"},"name":"User accepts the privacy settings","result":{"duration":162516800,"status":"passed"}},{"keyword":"And ","line":11,"match":{"location":"stepdefinitions.F2_RentBuyCalculator.user_sees_the_mortgages_tab()"},"name":"User sees the Mortgages tab","result":{"duration":23777100,"status":"passed"}},{"keyword":"And ","line":12,"match":{"location":"stepdefinitions.F2_RentBuyCalculator.user_hovers_over_mortgages_tab()"},"name":"User hovers over Mortgages tab","result":{"duration":139404600,"status":"passed"}},{"keyword":"And ","line":13,"match":{"location":"stepdefinitions.F2_RentBuyCalculator.user_clicks_rent_vs_buy_calculator()"},"name":"User clicks Rent vs Buy Calculator","result":{"duration":1676977400,"status":"passed"}},{"keyword":"And ","line":14,"match":{"location":"stepdefinitions.F2_RentBuyCalculator.user_should_be_at_the_rent_vs_buy_calculator_page()"},"name":"User should be at the Rent vs Buy Calculator page","result":{"duration":64224000,"status":"passed"}},{"keyword":"And ","line":15,"match":{"location":"stepdefinitions.F2_RentBuyCalculator.user_should_see_the_calculator_fields()"},"name":"User should see the calculator fields","result":{"duration":19651100,"status":"passed"}}]},{"start_timestamp":"2025-10-24T18:58:57.471Z","line":52,"id":"as-a-user-i-want-to-calculate-how-much-money-i-can-save-in-a-registered-retirement-savings;user-should-be-able-to-see-the-mortgage-(loan)-amount-when-selecting-5%--10%-and-20%-down-payment-for-a;;4","type":"scenario","keyword":"Scenario Outline","name":"User should be able to see the mortgage (loan) amount when selecting 5%, 10% and 20% down payment for a","description":"  given purchase price.","steps":[{"keyword":"When ","line":40,"match":{"location":"stepdefinitions.F2_RentBuyCalculator.user_inputs_monthly_rent(java.lang.String)","arguments":[{"val":"\"2000\"","offset":25}]},"name":"User inputs monthly rent \"2000\"","result":{"duration":69227200,"status":"passed"}},{"keyword":"And ","line":41,"match":{"location":"stepdefinitions.F2_RentBuyCalculator.user_inputs_interest_rate_percent(java.lang.String)","arguments":[{"val":"\"6\"","offset":26}]},"name":"User inputs interest rate \"6\" percent","result":{"duration":235209000,"status":"passed"}},{"keyword":"And ","line":42,"match":{"location":"stepdefinitions.F2_RentBuyCalculator.user_selects_the_amortization_period(java.lang.String)","arguments":[{"val":"\"10 years\"","offset":30}]},"name":"User selects the amortization \"10 years\" period","result":{"duration":178519500,"status":"passed"}},{"keyword":"And ","line":43,"match":{"location":"stepdefinitions.F2_RentBuyCalculator.user_selects_the_down_payment_percentage(java.lang.String)","arguments":[{"val":"\"20%\"","offset":30}]},"name":"User selects the down payment \"20%\" percentage","result":{"duration":173687400,"status":"passed"}},{"keyword":"And ","line":44,"match":{"location":"stepdefinitions.F2_RentBuyCalculator.user_clicks_calculate_button_in_rent_vs_buy_calculator()"},"name":"User clicks calculate button in rent vs buy calculator","result":{"duration":149747300,"status":"passed"}},{"keyword":"Then ","line":45,"match":{"location":"stepdefinitions.F2_RentBuyCalculator.user_should_be_able_to_see_cards_for_and_down_payment()"},"name":"User should be able to see 3 cards for 5%, 10% and 20% down payment","result":{"duration":760515400,"status":"passed"}},{"keyword":"And ","line":46,"match":{"location":"stepdefinitions.F2_RentBuyCalculator.userShouldBeAbleToSeeTheTotalMortgage(java.lang.String,java.lang.String,java.lang.String)","arguments":[{"val":"\"$182,943\"","offset":46},{"val":"\"$194,792\"","offset":57},{"val":"\"$225,935\"","offset":68}]},"name":"User should be able to see the total mortgage \"$182,943\" \"$194,792\" \"$225,935\"","result":{"duration":110970900,"status":"passed"}}],"before":[{"match":{"location":"stepdefinitions.Hooks.init()"},"result":{"duration":851611200,"status":"passed"}}],"after":[{"match":{"location":"stepdefinitions.Hooks.tearDown()"},"result":{"duration":206187300,"status":"passed"}}],"tags":[{"name":"@RentBuyCalculator"},{"name":"@RegressionTest"},{"name":"@MortgageRentResult"}]}],"tags":[{"name":"@RentBuyCalculator","type":"Tag","location":{"line":3,"column":1}},{"name":"@RegressionTest","type":"Tag","location":{"line":3,"column":20}}]},{"line":4,"uri":"file:src/test/resources/features/F3_ATMLocator.feature","id":"as-a-user-i-want-to-locate-the-nearest-atm-to-an-specific-address-so-that-i-can-plan-ahead-on-a-visit","keyword":"Feature","name":"As a user I want to locate the nearest ATM to an specific address so that I can plan ahead on a visit","description":"","elements":[{"line":6,"type":"background","keyword":"Background","name":"","description":"","steps":[{"keyword":"Given ","line":7,"match":{"location":"stepdefinitions.F1_RRSPCalculator.user_launches_the_application()"},"name":"User launches the application","result":{"duration":1271094500,"status":"passed"}},{"keyword":"And ","line":8,"match":{"location":"stepdefinitions.F1_RRSPCalculator.user_should_be_at_the_homepage()"},"name":"User should be at the homepage","result":{"duration":1039224800,"status":"passed"}},{"keyword":"And ","line":9,"match":{"location":"stepdefinitions.F1_RRSPCalculator.userAcceptsThePrivacySettings()"},"name":"User accepts the privacy settings","result":{"duration":195878900,"status":"passed"}}]},{"start_timestamp":"2025-10-24T18:59:04.737Z","line":12,"id":"as-a-user-i-want-to-locate-the-nearest-atm-to-an-specific-address-so-that-i-can-plan-ahead-on-a-visit;test-that-user-gets-instructions-on-how-to-use-the-search-if-no-address-is-provided","type":"scenario","keyword":"Scenario","name":"Test that user gets instructions on how to use the search if no address is provided","description":"","steps":[{"keyword":"When ","line":13,"match":{"location":"stepdefinitions.F3_ATMLocator.user_clicks_search_address_button()"},"name":"User clicks search address button","result":{"duration":1797453100,"status":"passed"}},{"keyword":"Then ","line":14,"match":{"location":"stepdefinitions.F3_ATMLocator.userShouldSeeAWhereMessage(java.lang.String)","arguments":[{"val":"\"Where are you located?\"","offset":41}]},"name":"User should see a Where are you located? \"Where are you located?\" message","result":{"duration":23257600,"status":"passed"}},{"keyword":"And ","line":15,"match":{"location":"stepdefinitions.F3_ATMLocator.userShouldSeeAShareLocationButton(java.lang.String)","arguments":[{"val":"\"Share Your Location\"","offset":38}]},"name":"User should see a Share Your Location \"Share Your Location\" button","result":{"duration":20992500,"status":"passed"}}],"before":[{"match":{"location":"stepdefinitions.Hooks.init()"},"result":{"duration":865581900,"status":"passed"}}],"after":[{"match":{"location":"stepdefinitions.Hooks.tearDown()"},"result":{"duration":192936900,"status":"passed"}}],"tags":[{"name":"@NearestATM"},{"name":"@RegressionTest"},{"name":"@AddressNotProvided"}]},{"line":6,"type":"background","keyword":"Background","name":"","description":"","steps":[{"keyword":"Given ","line":7,"match":{"location":"stepdefinitions.F1_RRSPCalculator.user_launches_the_application()"},"name":"User launches the application","result":{"duration":1334904700,"status":"passed"}},{"keyword":"And ","line":8,"match":{"location":"stepdefinitions.F1_RRSPCalculator.user_should_be_at_the_homepage()"},"name":"User should be at the homepage","result":{"duration":1030950700,"status":"passed"}},{"keyword":"And ","line":9,"match":{"location":"stepdefinitions.F1_RRSPCalculator.userAcceptsThePrivacySettings()"},"name":"User accepts the privacy settings","result":{"duration":174318400,"status":"passed"}}]},{"start_timestamp":"2025-10-24T18:59:10.146Z","line":27,"id":"as-a-user-i-want-to-locate-the-nearest-atm-to-an-specific-address-so-that-i-can-plan-ahead-on-a-visit;test-that-user-gets-the-correct-closest-branches-or-atms-given-an-specific-address;;2","type":"scenario","keyword":"Scenario Outline","name":"Test that user gets the correct closest branches or atms given an specific address","description":"","steps":[{"keyword":"When ","line":19,"match":{"location":"stepdefinitions.F3_ATMLocator.user_inputs_an_address(java.lang.String)","arguments":[{"val":"\"130 Adelaide\"","offset":23}]},"name":"User inputs an address \"130 Adelaide\"","result":{"duration":107144800,"status":"passed"}},{"keyword":"And ","line":20,"match":{"location":"stepdefinitions.F3_ATMLocator.user_clicks_search_address_button()"},"name":"User clicks search address button","result":{"duration":1858435700,"status":"passed"}},{"keyword":"Then ","line":21,"match":{"location":"stepdefinitions.F3_ATMLocator.user_should_be_able_to_see_closest_atm_or_branch_suggestions(int)","arguments":[{"val":"10","offset":27}]},"name":"User should be able to see 10 closest ATM or branch suggestions","result":{"duration":16888300,"status":"passed"}},{"keyword":"Then ","line":22,"match":{"location":"stepdefinitions.F3_ATMLocator.userShouldBeAbleToSeeTheCards()"},"name":"User should be able to see the cards","result":{"duration":17670300,"status":"passed"}},{"keyword":"And ","line":23,"match":{"location":"stepdefinitions.F3_ATMLocator.userShouldBeAbleToSee(java.lang.String)","arguments":[{"val":"\"Adelaide & York\"","offset":27}]},"name":"User should be able to see \"Adelaide & York\"","result":{"duration":26278500,"status":"passed"}}],"before":[{"match":{"location":"stepdefinitions.Hooks.init()"},"result":{"duration":867994800,"status":"passed"}}],"after":[{"match":{"location":"stepdefinitions.Hooks.tearDown()"},"result":{"duration":254148900,"status":"passed"}}],"tags":[{"name":"@NearestATM"},{"name":"@RegressionTest"},{"name":"@ProvidedAddress"}]},{"line":6,"type":"background","keyword":"Background","name":"","description":"","steps":[{"keyword":"Given ","line":7,"match":{"location":"stepdefinitions.F1_RRSPCalculator.user_launches_the_application()"},"name":"User launches the application","result":{"duration":1284329300,"status":"passed"}},{"keyword":"And ","line":8,"match":{"location":"stepdefinitions.F1_RRSPCalculator.user_should_be_at_the_homepage()"},"name":"User should be at the homepage","result":{"duration":1047273500,"status":"passed"}},{"keyword":"And ","line":9,"match":{"location":"stepdefinitions.F1_RRSPCalculator.userAcceptsThePrivacySettings()"},"name":"User accepts the privacy settings","result":{"duration":174504400,"status":"passed"}}]},{"start_timestamp":"2025-10-24T18:59:15.845Z","line":28,"id":"as-a-user-i-want-to-locate-the-nearest-atm-to-an-specific-address-so-that-i-can-plan-ahead-on-a-visit;test-that-user-gets-the-correct-closest-branches-or-atms-given-an-specific-address;;3","type":"scenario","keyword":"Scenario Outline","name":"Test that user gets the correct closest branches or atms given an specific address","description":"","steps":[{"keyword":"When ","line":19,"match":{"location":"stepdefinitions.F3_ATMLocator.user_inputs_an_address(java.lang.String)","arguments":[{"val":"\"222 Queen St\"","offset":23}]},"name":"User inputs an address \"222 Queen St\"","result":{"duration":97369800,"status":"passed"}},{"keyword":"And ","line":20,"match":{"location":"stepdefinitions.F3_ATMLocator.user_clicks_search_address_button()"},"name":"User clicks search address button","result":{"duration":1759028400,"status":"passed"}},{"keyword":"Then ","line":21,"match":{"location":"stepdefinitions.F3_ATMLocator.user_should_be_able_to_see_closest_atm_or_branch_suggestions(int)","arguments":[{"val":"10","offset":27}]},"name":"User should be able to see 10 closest ATM or branch suggestions","result":{"duration":25739600,"status":"passed"}},{"keyword":"Then ","line":22,"match":{"location":"stepdefinitions.F3_ATMLocator.userShouldBeAbleToSeeTheCards()"},"name":"User should be able to see the cards","result":{"duration":25508200,"status":"passed"}},{"keyword":"And ","line":23,"match":{"location":"stepdefinitions.F3_ATMLocator.userShouldBeAbleToSee(java.lang.String)","arguments":[{"val":"\"Petro-Canada\"","offset":27}]},"name":"User should be able to see \"Petro-Canada\"","result":{"duration":21444900,"status":"passed"}}],"before":[{"match":{"location":"stepdefinitions.Hooks.init()"},"result":{"duration":868315500,"status":"passed"}}],"after":[{"match":{"location":"stepdefinitions.Hooks.tearDown()"},"result":{"duration":240296000,"status":"passed"}}],"tags":[{"name":"@NearestATM"},{"name":"@RegressionTest"},{"name":"@ProvidedAddress"}]},{"line":6,"type":"background","keyword":"Background","name":"","description":"","steps":[{"keyword":"Given ","line":7,"match":{"location":"stepdefinitions.F1_RRSPCalculator.user_launches_the_application()"},"name":"User launches the application","result":{"duration":1456374300,"status":"passed"}},{"keyword":"And ","line":8,"match":{"location":"stepdefinitions.F1_RRSPCalculator.user_should_be_at_the_homepage()"},"name":"User should be at the homepage","result":{"duration":1035608600,"status":"passed"}},{"keyword":"And ","line":9,"match":{"location":"stepdefinitions.F1_RRSPCalculator.userAcceptsThePrivacySettings()"},"name":"User accepts the privacy settings","result":{"duration":156626400,"status":"passed"}}]},{"start_timestamp":"2025-10-24T18:59:21.395Z","line":29,"id":"as-a-user-i-want-to-locate-the-nearest-atm-to-an-specific-address-so-that-i-can-plan-ahead-on-a-visit;test-that-user-gets-the-correct-closest-branches-or-atms-given-an-specific-address;;4","type":"scenario","keyword":"Scenario Outline","name":"Test that user gets the correct closest branches or atms given an specific address","description":"","steps":[{"keyword":"When ","line":19,"match":{"location":"stepdefinitions.F3_ATMLocator.user_inputs_an_address(java.lang.String)","arguments":[{"val":"\"720 King St\"","offset":23}]},"name":"User inputs an address \"720 King St\"","result":{"duration":99405500,"status":"passed"}},{"keyword":"And ","line":20,"match":{"location":"stepdefinitions.F3_ATMLocator.user_clicks_search_address_button()"},"name":"User clicks search address button","result":{"duration":3154007100,"status":"passed"}},{"keyword":"Then ","line":21,"match":{"location":"stepdefinitions.F3_ATMLocator.user_should_be_able_to_see_closest_atm_or_branch_suggestions(int)","arguments":[{"val":"10","offset":27}]},"name":"User should be able to see 10 closest ATM or branch suggestions","result":{"duration":13424700,"status":"passed"}},{"keyword":"Then ","line":22,"match":{"location":"stepdefinitions.F3_ATMLocator.userShouldBeAbleToSeeTheCards()"},"name":"User should be able to see the cards","result":{"duration":19903000,"status":"passed"}},{"keyword":"And ","line":23,"match":{"location":"stepdefinitions.F3_ATMLocator.userShouldBeAbleToSee(java.lang.String)","arguments":[{"val":"\"RBC The Well On Front\"","offset":27}]},"name":"User should be able to see \"RBC The Well On Front\"","result":{"duration":25696900,"status":"passed"}}],"before":[{"match":{"location":"stepdefinitions.Hooks.init()"},"result":{"duration":840637800,"status":"passed"}}],"after":[{"match":{"location":"stepdefinitions.Hooks.tearDown()"},"result":{"duration":241337700,"status":"passed"}}],"tags":[{"name":"@NearestATM"},{"name":"@RegressionTest"},{"name":"@ProvidedAddress"}]}],"tags":[{"name":"@NearestATM","type":"Tag","location":{"line":3,"column":1}},{"name":"@RegressionTest","type":"Tag","location":{"line":3,"column":13}}]}]